samadb/__init__.py
samadb/samadb.py
samadb-0.3.0.dist-info/METADATA
samadb-0.3.0.dist-info/WHEEL
samadb-0.3.0.dist-info/top_level.txt
samadb-0.3.0.dist-info/RECORD
