Metadata-Version: 2.1
Name: samadb
Version: 0.3.0
Summary: An API providing access to a relational database with macroeconomic data for South Africa.
Author: Sebastian Krantz
Author-email: sebastian.krantz@graduateinstitute.ch
License: GPL-3
Project-URL: Bug Reports, https://github.com/Stellenbosch-Econometrics/SAMADB-Issues/issues
Keywords: south africa,macroeconomic,data,API
Classifier: Development Status :: 5 - Production/Stable
Classifier: License :: OSI Approved :: GNU General Public License v3 (GPLv3)
Classifier: Programming Language :: Python :: 3
Requires-Python: >=3.1
Requires-Dist: connectorx
Requires-Dist: pyarrow
Requires-Dist: polars
